	<Group Id="{a34d054f-ec5d-4cd5-a8c3-c202947a022d}" Type="Device">
		<!-- ./Vendor/MSFT/Defender/Configuration/DeviceControl/PolicyGroups/%7Ba34d054f-ec5d-4cd5-a8c3-c202947a022d%7D/GroupData -->
		<Name>Authorized USBs</Name>
		<MatchType>MatchAny</MatchType>
		<DescriptorIdList>
			<!--Device A-->
			<VID_PID>0781_5567</VID_PID>
			<!--Device B-->
			<VID_PID>046d_a120</VID_PID>
			<!--Device C-->
			<VID_PID>046d_a0b1</VID_PID>
			<!--Device D-->
			<VID_PID>046d_0825</VID_PID>
			<!--Device E-->
			<VID_PID>AAAA_BBBB</VID_PID>
			<!--Device F-->
			<VID_PID>FFFF_2222</VID_PID>
		</DescriptorIdList>
	</Group>